ucdp_regf-15.0.0.dist-info/METADATA
ucdp_regf-15.0.0.dist-info/WHEEL
ucdp_regf-15.0.0.dist-info/entry_points.txt
ucdp_regf-15.0.0.dist-info/licenses/LICENSE
ucdp_regf/__init__.py
ucdp_regf/examples/simple/fileliststandard.py
ucdp_regf/examples/simple/glbl/__init__.py
ucdp_regf/examples/simple/glbl/bus.py
ucdp_regf/examples/simple/glbl/bus2mem.py
ucdp_regf/examples/simple/glbl/clk_gate.py
ucdp_regf/examples/simple/glbl/regf.py
ucdp_regf/examples/simple/src/glbl/bus2mem/rtl/bus2mem.sv
ucdp_regf/examples/simple/uart/__init__.py
ucdp_regf/examples/simple/uart/uart.py
ucdp_regf/ucdp-templates/ucdp_regf.sv.mako
ucdp_regf/ucdp_regf.py
ucdp_regf/util.py
ucdp_regf-15.0.0.dist-info/RECORD
