Metadata-Version: 2.1
Name: ucdp-regf
Version: 15.0.0
Summary: Unified Chip Design Platform - Register File
Classifier: Programming Language :: Python :: 3
Classifier: Operating System :: OS Independent
Project-URL: Homepage, https://github.com/nbiotcloud/ucdp-regf
Project-URL: Documentation, https://ucdp-regf.readthedocs.io/en/stable/
Project-URL: Bug Tracker, https://github.com/nbiotcloud/ucdp-regf/issues
Requires-Python: <4.0,>=3.10.0
Requires-Dist: ucdp-addr>=1.8.2
